{
  "comment": "neat",
  "steps": [
    {
      "comment": null,
      "directory_statuses": {
        "/Users/david/projects/airtable-adding-games": "completed",
        "/Users/david/projects/ref-haus": "completed",
        "/Users/david/projects/shellprints": "failed"
      },
      "slug": "clean-status"
    },
    {
      "comment": null,
      "directory_statuses": {
        "/Users/david/projects/airtable-adding-games": "failed",
        "/Users/david/projects/ref-haus": "completed"
      },
      "slug": "git-pull"
    },
    {
      "comment": null,
      "directory_statuses": {
        "/Users/david/projects/ref-haus": "completed"
      },
      "slug": "clean-status"
    }
  ],
  "directories": [
    "/Users/david/projects/airtable-adding-games",
    "/Users/david/projects/ref-haus",
    "/Users/david/projects/shellprints"
  ]
}